setup.py
asyncgridfs/__init__.py
asyncgridfs.egg-info/PKG-INFO
asyncgridfs.egg-info/SOURCES.txt
asyncgridfs.egg-info/dependency_links.txt
asyncgridfs.egg-info/requires.txt
asyncgridfs.egg-info/top_level.txt
test/test_gridfs.py