Metadata-Version: 1.0
Name: asyncgridfs
Version: 0.1.dev
Summary: async mongodb gridfs with tornado IOLoop
Home-page: http://github.com/comger/asyncmongo
Author: comger@gmail.com
Author-email: comger@gmail.com
License: https://github.com/comger/asyncgridfs/blob/master/LICENSE
Keywords: asyncmongo,gridfs,tornado
Platform: UNKNOWN
Classifier: License :: OSI Approved :: Apache Software License
Classifier: Programming Language :: Python :: 2
Classifier: Programming Language :: Python :: 2.6
Classifier: Programming Language :: Python :: 2.7
Classifier: Programming Language :: Python :: Implementation :: CPython
Classifier: Programming Language :: Python :: Implementation :: PyPy
